[
  {
    "id":"204059X",
    "name": "Jhon Snow",
    "reviewed": "Not Reviewed",
    "comments": "No Comments yet",
    "rate": 0 
  },
  {
    "id":"194058V",
    "name": "Jack Dawson",
    "reviewed": "Reviewed",
    "comments": "Check for more" ,
    "rate": 65  
  },
  {
    "id":"215678H",
    "name": "Tom Shelby",
    "reviewed": "Error",
    "comments": "No comments yet" ,
    "rate": 90    
  },
  {
    "id":"204655F",
    "name": "Walter White",
    "reviewed": "Reviewed",
    "comments": "Excellent",
    "rate": 0     
  }
]
